{"browsers":{"82711586":{"id":"82711586","fullName":"Mozilla/5.0 (Windows NT 10.0; Win64; x64) AppleWebKit/537.36 (KHTML, like Gecko) Chrome/87.0.4280.66 Safari/537.36","name":"Chrome 87.0.4280.66 (Windows 10)","state":"DISCONNECTED","lastResult":{"startTime":1605878758407,"total":1,"success":1,"failed":0,"skipped":0,"totalTime":125,"netTime":26,"error":false,"disconnected":false},"disconnectsCount":0,"noActivityTimeout":30000,"disconnectDelay":2000}},"result":{"82711586":[{"fullName":"AppComponent should have a title","description":"should have a title","id":"spec0","log":[],"skipped":false,"disabled":false,"pending":false,"success":true,"suite":["AppComponent"],"time":26,"executedExpectationsCount":1,"passedExpectations":[{"matcherName":"toContain","message":"Passed.","stack":"","passed":true}],"properties":null}]},"summary":{"success":1,"failed":0,"skipped":0,"error":false,"disconnected":false,"exitCode":0}}